{
  "categories": [
    {
      "id": "tenses",
      "title": "Времена",
      "topics": [
        {
          "id": "как-устроена-система-времён",
          "title": "Как устроена система времён",
          "group": null,
          "level": null,
          "html": "<p>В английском <strong>3 времени</strong> (настоящее, прошедшее, будущее) × <strong>4 аспекта</strong> = <strong>12 форм</strong>.</p>\n<table><thead><tr><th></th><th>Simple (простое)</th><th>Continuous (длительное)</th><th>Perfect (совершённое)</th><th>Perfect Continuous</th></tr></thead><tbody><tr><td><strong>Present</strong></td><td>I work</td><td>I am working</td><td>I have worked</td><td>I have been working</td></tr><tr><td><strong>Past</strong></td><td>I worked</td><td>I was working</td><td>I had worked</td><td>I had been working</td></tr><tr><td><strong>Future</strong></td><td>I will work</td><td>I will be working</td><td>I will have worked</td><td>I will have been working</td></tr></tbody></table>\n<p><strong>Что означает каждый аспект:</strong></p>\n<ul><li><strong>Simple</strong> — факт. Просто сообщаю, что действие есть/было/будет.</li><li><strong>Continuous</strong> — процесс. Действие длится, оно не закончено в момент, о котором говорим.</li><li><strong>Perfect</strong> — результат. Действие завершилось <strong>к какому-то моменту</strong>, важен итог.</li><li><strong>Perfect Continuous</strong> — длительность до момента. Действие шло какое-то время и подводит к точке.</li></ul>\n<p>Понял эти 4 аспекта — понял всю систему. Дальше остаётся только менять время (present/past/future).</p>\n<hr>"
        },
        {
          "id": "present-simple",
          "title": "Present Simple",
          "group": "Настоящее время",
          "level": "A1",
          "html": "<h3>Зачем нужно</h3>\n<p>Говорим о том, что <strong>происходит регулярно</strong> или <strong>является правдой вообще</strong>.</p>\n<p>Три случая:</p>\n<ol><li><strong>Привычки и рутина</strong> — то, что повторяется</li><li><strong>Общие истины и факты</strong> — то, что верно всегда</li><li><strong>Расписания</strong> — поезда, уроки, фильмы</li></ol>\n<h3>Формула</h3>\n<pre><code>+  I / you / we / they  +  V           →  I work\n   he / she / it        +  V + s       →  He works\n\n−  I / you / we / they  +  don't + V   →  I don't work\n   he / she / it        +  doesn't + V →  He doesn't work\n\n?  Do   + I/you/we/they + V ?          →  Do you work?\n   Does + he/she/it     + V ?          →  Does he work?</code></pre>\n<p><strong>Главная ловушка:</strong> окончание <strong>-s</strong> в 3-м лице единственного числа (he/she/it).</p>\n<p>Ошибка <code>He work</code> — самая частая ошибка новичков.</p>\n<p><strong>Правила добавления -s:</strong></p>\n<table><thead><tr><th>Окончание глагола</th><th>Что добавляем</th><th>Пример</th></tr></thead><tbody><tr><td>обычный глагол</td><td>+ s</td><td>work → works</td></tr><tr><td>-s, -ss, -sh, -ch, -x, -o</td><td>+ es</td><td>go → goes, watch → watches</td></tr><tr><td>согласная + y</td><td>y → ies</td><td>study → studies</td></tr><tr><td>гласная + y</td><td>+ s</td><td>play → plays</td></tr></tbody></table>\n<h3>Слова-маркеры</h3>\n<p><code>always, usually, often, sometimes, rarely, never, every day/week/year, on Mondays, twice a week</code></p>\n<p>Эти слова обычно стоят <strong>перед смысловым глаголом</strong>, но <strong>после</strong> глагола to be:</p>\n<ul><li>I <strong>often</strong> go to the gym.</li><li>She is <strong>often</strong> late. ← после is</li></ul>\n<h3>Примеры</h3>\n<ul><li>I <strong>drink</strong> coffee every morning. <em>(привычка)</em></li><li>Water <strong>boils</strong> at 100 degrees. <em>(общая истина)</em></li><li>The train <strong>leaves</strong> at 7:15. <em>(расписание)</em></li><li>She <strong>doesn't like</strong> fish. <em>(отрицание)</em></li><li><strong>Do</strong> you <strong>speak</strong> English? <em>(вопрос)</em></li></ul>\n<h3>Типичные ошибки</h3>\n<table><thead><tr><th>❌ Неверно</th><th>✅ Верно</th><th>Почему</th></tr></thead><tbody><tr><td>He work here.</td><td>He <strong>works</strong> here.</td><td>забыли -s в 3-м лице</td></tr><tr><td>She doesn't <strong>works</strong>.</td><td>She doesn't <strong>work</strong>.</td><td>после does/doesn't глагол без -s</td></tr><tr><td><strong>Do</strong> he like it?</td><td><strong>Does</strong> he like it?</td><td>для he/she/it — does</td></tr><tr><td>I am work every day.</td><td>I <strong>work</strong> every day.</td><td>Present Simple не нужен to be</td></tr></tbody></table>\n<hr>"
        },
        {
          "id": "present-continuous",
          "title": "Present Continuous",
          "group": "Настоящее время",
          "level": "A1/A2",
          "html": "<h3>Зачем нужно</h3>\n<p>Действие <strong>происходит прямо сейчас</strong> или <strong>в текущий период</strong> (не обязательно в эту секунду).</p>\n<p>Случаи:</p>\n<ol><li><strong>Прямо сейчас</strong> — в момент речи</li><li><strong>В текущий период</strong> — этот месяц, эти дни (но не в эту секунду)</li><li><strong>Запланированное будущее</strong> — договорённость с конкретным временем</li><li><strong>Раздражающая привычка</strong> — с always (эмоциональная окраска)</li></ol>\n<h3>Формула</h3>\n<pre><code>+  am / is / are  +  V-ing        →  I am working / He is working\n−  am / is / are  +  not + V-ing  →  I am not working\n?  Am / Is / Are  +  подл + V-ing? →  Are you working?</code></pre>\n<p><strong>Правила добавления -ing:</strong></p>\n<table><thead><tr><th>Ситуация</th><th>Что делаем</th><th>Пример</th></tr></thead><tbody><tr><td>обычный глагол</td><td>+ ing</td><td>work → working</td></tr><tr><td>немая -e на конце</td><td>убираем e, + ing</td><td>make → making</td></tr><tr><td>одна гласная + согласная (ударный слог)</td><td>удваиваем согласную</td><td>sit → sitting, run → running</td></tr><tr><td>-ie на конце</td><td>ie → y + ing</td><td>lie → lying</td></tr></tbody></table>\n<h3>Слова-маркеры</h3>\n<p><code>now, right now, at the moment, currently, today, this week, look!, listen!</code></p>\n<h3>Примеры</h3>\n<ul><li>I <strong>am reading</strong> a book right now. <em>(сейчас)</em></li><li>She <strong>is studying</strong> French this year. <em>(текущий период — но не в эту секунду)</em></li><li>We <strong>are meeting</strong> John tomorrow at 6. <em>(запланированное будущее)</em></li><li>He <strong>is always losing</strong> his keys! <em>(раздражающая привычка)</em></li></ul>\n<h3>⚠️ Глаголы состояния (State Verbs)</h3>\n<p>Некоторые глаголы <strong>не используются в Continuous</strong> — они описывают состояние, а не процесс.</p>\n<table><thead><tr><th>Категория</th><th>Глаголы</th></tr></thead><tbody><tr><td>Чувства/восприятие</td><td>see, hear, smell, taste, feel</td></tr><tr><td>Мнение/знание</td><td>know, understand, believe, think*, remember, forget</td></tr><tr><td>Эмоции</td><td>like, love, hate, want, need, prefer</td></tr><tr><td>Обладание</td><td>have*, own, belong, possess</td></tr><tr><td>Бытие</td><td>be<em>, seem, look</em>, appear</td></tr></tbody></table>\n<p>❌ I am knowing the answer. → ✅ I <strong>know</strong> the answer.</p>\n<p>❌ I am wanting coffee. → ✅ I <strong>want</strong> coffee.</p>\n<p><strong>Исключения</strong> (глаголы со звёздочкой меняют смысл):</p>\n<ul><li>I <strong>think</strong> it's good. <em>(мнение)</em> / I <strong>am thinking</strong> about it. <em>(процесс размышления)</em></li><li>She <strong>has</strong> a car. <em>(владеет)</em> / She <strong>is having</strong> lunch. <em>(ест — процесс)</em></li><li>He <strong>looks</strong> tired. <em>(выглядит)</em> / He <strong>is looking</strong> at me. <em>(смотрит)</em></li></ul>\n<hr>"
        },
        {
          "id": "сравнение-present-simple-vs-present-continuous",
          "title": "Сравнение: Present Simple vs Present Continuous",
          "group": "Настоящее время",
          "level": null,
          "html": "<p>Самая частая путаница на уровне A1–A2.</p>\n<table><thead><tr><th></th><th>Present Simple</th><th>Present Continuous</th></tr></thead><tbody><tr><td><strong>Смысл</strong></td><td>вообще, регулярно</td><td>сейчас, временно</td></tr><tr><td><strong>Вопрос</strong></td><td>что делаешь по жизни?</td><td>что делаешь в данный момент?</td></tr><tr><td><strong>Пример</strong></td><td>I <strong>work</strong> in a bank. <em>(это моя работа)</em></td><td>I <strong>am working</strong> now. <em>(я сейчас за работой)</em></td></tr><tr><td><strong>Маркеры</strong></td><td>always, usually, every day</td><td>now, at the moment, today</td></tr></tbody></table>\n<p><strong>Ключевая пара для понимания:</strong></p>\n<ul><li>What <strong>do</strong> you <strong>do</strong>? → Я спрашиваю про <strong>профессию</strong>. <em>(«Кем работаешь?»)</em></li><li>What <strong>are</strong> you <strong>doing</strong>? → Я спрашиваю, <strong>чем занят сейчас</strong>. <em>(«Что делаешь?»)</em></li></ul>\n<hr>"
        },
        {
          "id": "present-perfect-b1-самое-сложное-для-русскоговорящих",
          "title": "Present Perfect — B1 ⭐ (самое сложное для русскоговорящих)",
          "group": "Настоящее время",
          "level": null,
          "html": "<h3>Почему это сложно</h3>\n<p>В русском языке <strong>нет</strong> аналога. Мы говорим «Я сделал» и для «только что сделал», и для «сделал вчера». В английском это <strong>разные времена</strong>.</p>\n<h3>Зачем нужно</h3>\n<p>Действие в прошлом, которое <strong>связано с настоящим</strong>. Важен не сам момент, а <strong>результат сейчас</strong>.</p>\n<p>Четыре случая:</p>\n<p><strong>1. Опыт</strong> — делал ли когда-нибудь (неважно когда)</p>\n<ul><li>I <strong>have been</strong> to Paris. <em>(был — есть такой опыт)</em></li></ul>\n<p><strong>2. Результат виден сейчас</strong></p>\n<ul><li>I <strong>have lost</strong> my keys. <em>(потерял — и до сих пор не нашёл)</em></li></ul>\n<p><strong>3. Незаконченный период времени</strong></p>\n<ul><li>I <strong>have seen</strong> three films <strong>this week</strong>. <em>(неделя ещё не кончилась)</em></li></ul>\n<p><strong>4. Действие только что завершилось</strong></p>\n<ul><li>She <strong>has just finished</strong> her homework.</li></ul>\n<h3>Формула</h3>\n<pre><code>+  have / has  +  V3 (past participle)   →  I have worked / He has worked\n−  haven't / hasn't  +  V3               →  I haven't worked\n?  Have / Has  +  подл + V3 ?            →  Have you worked?</code></pre>\n<p><strong>V3</strong> — третья форма глагола (причастие прошедшего времени):</p>\n<ul><li>правильные: work → work<strong>ed</strong></li><li>неправильные: go → <strong>gone</strong>, see → <strong>seen</strong>, do → <strong>done</strong> <em>(нужно учить)</em></li></ul>\n<h3>Слова-маркеры</h3>\n<table><thead><tr><th>Маркер</th><th>Значение</th><th>Пример</th></tr></thead><tbody><tr><td><strong>just</strong></td><td>только что</td><td>I have just eaten.</td></tr><tr><td><strong>already</strong></td><td>уже (в +)</td><td>She has already left.</td></tr><tr><td><strong>yet</strong></td><td>ещё (в − и ?)</td><td>Have you finished <strong>yet</strong>? / I haven't finished <strong>yet</strong>.</td></tr><tr><td><strong>ever</strong></td><td>когда-нибудь (в ?)</td><td>Have you <strong>ever</strong> been to Japan?</td></tr><tr><td><strong>never</strong></td><td>никогда</td><td>I have <strong>never</strong> seen snow.</td></tr><tr><td><strong>for</strong></td><td>в течение (период)</td><td>I have lived here <strong>for</strong> 5 years.</td></tr><tr><td><strong>since</strong></td><td>с (точка отсчёта)</td><td>I have lived here <strong>since</strong> 2019.</td></tr><tr><td><strong>recently / lately</strong></td><td>недавно</td><td>He has recently changed jobs.</td></tr><tr><td><strong>so far / up to now</strong></td><td>пока что</td><td>We have finished 3 tasks <strong>so far</strong>.</td></tr></tbody></table>\n<h3>for vs since — важное различие</h3>\n<pre><code>for   + ПЕРИОД      →  for two hours, for a week, for ten years\nsince + ТОЧКА       →  since Monday, since 2020, since I was a child</code></pre>\n<ul><li>I have known him <strong>for</strong> ten years. <em>(сколько длится)</em></li><li>I have known him <strong>since</strong> 2015. <em>(с какого момента)</em></li></ul>\n<h3>Примеры</h3>\n<ul><li>I <strong>have finished</strong> my work. <em>(результат: работа готова)</em></li><li><strong>Have</strong> you <strong>ever</strong> <strong>tried</strong> sushi? <em>(опыт)</em></li><li>She <strong>has lived</strong> here <strong>since</strong> 2020. <em>(началось в прошлом, длится сейчас)</em></li><li>They <strong>haven't arrived</strong> <strong>yet</strong>. <em>(ожидаем — до сих пор нет)</em></li></ul>\n<hr>"
        },
        {
          "id": "present-perfect-vs-past-simple-главная-развилка",
          "title": "⭐ Present Perfect vs Past Simple — главная развилка",
          "group": "Настоящее время",
          "level": null,
          "html": "<p>Это <strong>самое важное сравнение</strong> во всей грамматике. Ошибка здесь — самая частая у русскоговорящих.</p>\n<h3>Правило одной фразы</h3>\n<blockquote><p><strong>Есть конкретное завершённое время в прошлом → Past Simple.<br>Нет времени / время не закончилось / важен результат → Present Perfect.</strong></p></blockquote>\n<h3>Таблица</h3>\n<table><thead><tr><th></th><th>Present Perfect</th><th>Past Simple</th></tr></thead><tbody><tr><td><strong>Когда</strong></td><td>время не указано или период не закончен</td><td>конкретное время в прошлом</td></tr><tr><td><strong>Фокус</strong></td><td>результат <strong>сейчас</strong></td><td>факт <strong>тогда</strong></td></tr><tr><td><strong>Маркеры</strong></td><td>just, already, yet, ever, never, for, since, this week</td><td>yesterday, last year, in 2010, ago, when I was</td></tr><tr><td><strong>Пример</strong></td><td>I <strong>have lost</strong> my keys. <em>(и сейчас без ключей)</em></td><td>I <strong>lost</strong> my keys <strong>yesterday</strong>. <em>(факт вчера)</em></td></tr></tbody></table>\n<h3>Ключевые пары</h3>\n<pre><code>✅ I have been to London.          ← был когда-то (опыт)\n✅ I went to London last year.     ← был в прошлом году (когда — известно)\n❌ I have been to London last year. ← НЕЛЬЗЯ: есть \"last year\"\n\n✅ Have you seen this film?        ← вообще смотрел?\n✅ Did you see this film yesterday? ← смотрел вчера?\n\n✅ She has written three books.     ← она жива, может написать ещё\n✅ She wrote three books.           ← она умерла, период закрыт</code></pre>\n<h3>Проверочный вопрос</h3>\n<p>Спроси себя: <strong>«Могу ли я назвать конкретное время?»</strong></p>\n<ul><li>Да (вчера, в 2010, час назад) → <strong>Past Simple</strong></li><li>Нет / период идёт (сегодня, на этой неделе, вообще) → <strong>Present Perfect</strong></li></ul>\n<h3>⚠️ Слово \"ago\" всегда требует Past Simple</h3>\n<ul><li>❌ I have finished it two hours ago.</li><li>✅ I <strong>finished</strong> it two hours <strong>ago</strong>.</li></ul>\n<hr>"
        },
        {
          "id": "present-perfect-continuous",
          "title": "Present Perfect Continuous",
          "group": "Настоящее время",
          "level": "B2",
          "html": "<h3>Зачем нужно</h3>\n<p>Действие <strong>началось в прошлом, длилось какое-то время и продолжается сейчас</strong> (или только что закончилось, и виден результат процесса).</p>\n<p>Акцент на <strong>длительности процесса</strong>, а не на результате.</p>\n<h3>Формула</h3>\n<pre><code>+  have / has  +  been  +  V-ing    →  I have been working\n−  haven't / hasn't + been + V-ing  →  I haven't been working\n?  Have / Has + подл + been + V-ing? →  Have you been working?</code></pre>\n<h3>Маркеры</h3>\n<p><code>for, since, all day, all morning, how long, lately, recently</code></p>\n<h3>Present Perfect vs Present Perfect Continuous</h3>\n<table><thead><tr><th></th><th>Perfect</th><th>Perfect Continuous</th></tr></thead><tbody><tr><td><strong>Фокус</strong></td><td>результат, сколько сделано</td><td>процесс, как долго</td></tr><tr><td><strong>Пример</strong></td><td>I <strong>have read</strong> three books. <em>(результат: 3 книги)</em></td><td>I <strong>have been reading</strong> all day. <em>(процесс: весь день)</em></td></tr><tr><td><strong>Вопрос</strong></td><td>How many?</td><td>How long?</td></tr></tbody></table>\n<p><strong>Ключевая пара:</strong></p>\n<ul><li>I <strong>have painted</strong> the room. → Комната покрашена. <em>(результат)</em></li><li>I <strong>have been painting</strong> the room. → Я весь в краске. <em>(процесс, объясняет моё состояние)</em></li></ul>\n<hr>"
        },
        {
          "id": "past-simple",
          "title": "Past Simple",
          "group": "Прошедшее время",
          "level": "A2",
          "html": "<h3>Зачем нужно</h3>\n<p>Действие <strong>завершилось в конкретный момент в прошлом</strong>. Момент известен или подразумевается.</p>\n<h3>Формула</h3>\n<pre><code>+  V2 (вторая форма)              →  I worked / I went\n−  didn't  +  V (первая форма!)   →  I didn't work / I didn't go\n?  Did  +  подл  +  V ?           →  Did you work? / Did you go?</code></pre>\n<p><strong>Важно:</strong> в отрицании и вопросе — <strong>did/didn't + первая форма</strong> глагола, без -ed:</p>\n<ul><li>❌ I didn't <strong>went</strong>. → ✅ I didn't <strong>go</strong>.</li><li>❌ <strong>Did</strong> you <strong>went</strong>? → ✅ <strong>Did</strong> you <strong>go</strong>?</li></ul>\n<p><strong>Правильные глаголы:</strong> + -ed (work → worked)</p>\n<p><strong>Неправильные глаголы:</strong> особая форма (go → went, see → saw, buy → bought) — нужно учить</p>\n<h3>Маркеры</h3>\n<p><code>yesterday, last week/month/year, ago, in 2010, when I was young, then, that day</code></p>\n<h3>Примеры</h3>\n<ul><li>I <strong>watched</strong> a film yesterday.</li><li>She <strong>went</strong> to Spain last summer.</li><li>We <strong>didn't see</strong> them at the party.</li><li><strong>Did</strong> you <strong>call</strong> her?</li></ul>\n<hr>"
        },
        {
          "id": "past-continuous",
          "title": "Past Continuous",
          "group": "Прошедшее время",
          "level": "B1",
          "html": "<h3>Зачем нужно</h3>\n<p>Действие <strong>длилось</strong> в определённый момент в прошлом (было в процессе).</p>\n<p>Случаи:</p>\n<ol><li><strong>Процесс в момент прошлого</strong> — что происходило в 8 вечера</li><li><strong>Фон для короткого действия</strong> — длинное действие прерывается коротким</li><li><strong>Два параллельных действия</strong> — оба длились одновременно</li></ol>\n<h3>Формула</h3>\n<pre><code>+  was / were  +  V-ing        →  I was working / They were working\n−  wasn't / weren't + V-ing    →  I wasn't working\n?  Was / Were + подл + V-ing?  →  Were you working?</code></pre>\n<p><code>was</code> — I, he, she, it</p>\n<p><code>were</code> — you, we, they</p>\n<h3>Past Simple + Past Continuous — классическая связка</h3>\n<p>Длинное действие (Continuous) <strong>прерывается</strong> коротким (Simple):</p>\n<pre><code>I was cooking dinner  |  when  |  the phone rang.\n   ← длинный процесс  |        |  ← короткое действие прервало</code></pre>\n<ul><li><strong>when</strong> + Past Simple <em>(короткое)</em></li><li><strong>while</strong> + Past Continuous <em>(длинное)</em></li></ul>\n<p>Примеры:</p>\n<ul><li>I <strong>was watching</strong> TV <strong>when</strong> she <strong>called</strong>.</li><li><strong>While</strong> I <strong>was walking</strong> home, I <strong>met</strong> an old friend.</li><li><strong>When</strong> he <strong>arrived</strong>, we <strong>were having</strong> dinner. <em>(мы уже ужинали, он пришёл в процессе)</em></li></ul>\n<hr>"
        },
        {
          "id": "past-perfect",
          "title": "Past Perfect",
          "group": "Прошедшее время",
          "level": "B2",
          "html": "<h3>Зачем нужно</h3>\n<p>Действие завершилось <strong>ДО другого действия в прошлом</strong>. «Предпрошедшее» время.</p>\n<p>Нужно, когда важен <strong>порядок</strong> двух прошедших событий.</p>\n<h3>Формула</h3>\n<pre><code>+  had  +  V3            →  I had worked\n−  hadn't  +  V3         →  I hadn't worked\n?  Had  +  подл + V3 ?   →  Had you worked?</code></pre>\n<p><code>had</code> — для всех лиц, не меняется.</p>\n<h3>Как это работает</h3>\n<pre><code>Прошлое ────────────────────────────────► Сейчас\n    │                    │\n Past Perfect        Past Simple\n (раньше)            (позже)</code></pre>\n<ul><li><strong>By the time</strong> we arrived, the film <strong>had already started</strong>.</li></ul>\n<p><em>(сначала фильм начался, потом мы пришли)</em></p>\n<ul><li>She <strong>had left</strong> before I <strong>called</strong>.</li></ul>\n<p><em>(сначала ушла, потом я позвонил)</em></p>\n<ul><li>I <strong>couldn't</strong> get in because I <strong>had lost</strong> my key.</li></ul>\n<p><em>(сначала потерял ключ, потом не смог войти)</em></p>\n<h3>Маркеры</h3>\n<p><code>before, after, by the time, already, just, never, when (в значении \"к тому моменту как\")</code></p>\n<h3>Когда Past Perfect НЕ нужен</h3>\n<p>Если действия идут <strong>по порядку</strong> и это очевидно — достаточно Past Simple:</p>\n<ul><li>I <strong>got up</strong>, <strong>had</strong> breakfast and <strong>went</strong> to work. <em>(последовательность ясна)</em></li></ul>\n<p>Past Perfect нужен, когда порядок <strong>нарушен</strong> в рассказе или его надо подчеркнуть.</p>\n<hr>"
        },
        {
          "id": "past-perfect-continuous",
          "title": "Past Perfect Continuous",
          "group": "Прошедшее время",
          "level": "C1",
          "html": "<h3>Зачем нужно</h3>\n<p>Действие <strong>длилось некоторое время ДО момента в прошлом</strong>.</p>\n<h3>Формула</h3>\n<pre><code>+  had been  +  V-ing         →  I had been working\n−  hadn't been + V-ing        →  I hadn't been working\n?  Had + подл + been + V-ing? →  Had you been working?</code></pre>\n<h3>Примеры</h3>\n<ul><li>She <strong>had been waiting</strong> for two hours <strong>when</strong> the train finally arrived.</li></ul>\n<p><em>(ждала 2 часа → потом поезд пришёл)</em></p>\n<ul><li>He was tired because he <strong>had been working</strong> all night.</li></ul>\n<p><em>(работал всю ночь → поэтому устал)</em></p>\n<p>Сравни:</p>\n<ul><li>He <strong>had worked</strong> there. <em>(факт: работал)</em></li><li>He <strong>had been working</strong> there <strong>for 5 years</strong> before he quit. <em>(длительность до момента)</em></li></ul>\n<hr>"
        },
        {
          "id": "future-simple-will",
          "title": "Future Simple (will)",
          "group": "Будущее время",
          "level": "A2",
          "html": "<h3>Зачем нужно</h3>\n<ol><li><strong>Спонтанное решение</strong> — решил прямо сейчас, в момент речи</li><li><strong>Предсказание/мнение</strong> — думаю, что так будет</li><li><strong>Обещание, предложение, отказ</strong></li><li><strong>Факт о будущем</strong> — то, что просто произойдёт</li></ol>\n<h3>Формула</h3>\n<pre><code>+  will  +  V           →  I will work\n−  won't  +  V          →  I won't work\n?  Will  +  подл + V ?  →  Will you work?</code></pre>\n<p><code>will</code> — для всех лиц. <code>won't</code> = will not.</p>\n<h3>Маркеры</h3>\n<p><code>tomorrow, next week/year, in the future, soon, probably, I think, I'm sure</code></p>\n<h3>Примеры</h3>\n<ul><li>The phone is ringing. I <strong>'ll get</strong> it! <em>(спонтанно, решил сейчас)</em></li><li>I think it <strong>will rain</strong> tomorrow. <em>(предсказание)</em></li><li>I <strong>'ll help</strong> you with the bags. <em>(предложение помощи)</em></li><li>She <strong>will be</strong> 30 next year. <em>(факт)</em></li></ul>\n<hr>"
        },
        {
          "id": "be-going-to",
          "title": "be going to",
          "group": "Будущее время",
          "level": "A2",
          "html": "<h3>Зачем нужно</h3>\n<ol><li><strong>План/намерение</strong> — решил <strong>заранее</strong>, до момента речи</li><li><strong>Предсказание по видимым признакам</strong> — вижу доказательство сейчас</li></ol>\n<h3>Формула</h3>\n<pre><code>am / is / are  +  going to  +  V   →  I am going to work</code></pre>\n<h3>⭐ will vs be going to — важное различие</h3>\n<table><thead><tr><th></th><th>will</th><th>be going to</th></tr></thead><tbody><tr><td><strong>Решение</strong></td><td>принято <strong>сейчас</strong>, спонтанно</td><td>принято <strong>заранее</strong></td></tr><tr><td><strong>Предсказание</strong></td><td>по мнению, ощущению</td><td>по <strong>видимым признакам</strong></td></tr></tbody></table>\n<p><strong>Решение:</strong></p>\n<ul><li>«У нас нет молока» → «О, я <strong>will buy</strong> it.» <em>(решил только что)</em></li><li>«Зачем идёшь в магазин?» → «Я <strong>am going to buy</strong> milk.» <em>(решил раньше)</em></li></ul>\n<p><strong>Предсказание:</strong></p>\n<ul><li>I think our team <strong>will win</strong>. <em>(мнение)</em></li><li>Look at those black clouds! It <strong>is going to rain</strong>. <em>(вижу тучи — доказательство)</em></li></ul>\n<hr>"
        },
        {
          "id": "present-continuous-для-будущего",
          "title": "Present Continuous для будущего",
          "group": "Будущее время",
          "level": "B1",
          "html": "<p>Когда есть <strong>договорённость</strong> с конкретным временем/местом (встреча в календаре).</p>\n<ul><li>I <strong>am meeting</strong> John at 6 tomorrow. <em>(договорились, время назначено)</em></li><li>We <strong>are flying</strong> to Rome on Friday. <em>(билеты куплены)</em></li></ul>\n<p>Разница с <em>be going to</em>:</p>\n<ul><li><strong>going to</strong> = намерение <em>(я собираюсь)</em></li><li><strong>Present Continuous</strong> = договорённость <em>(уже назначено)</em></li></ul>\n<hr>"
        },
        {
          "id": "future-continuous",
          "title": "Future Continuous",
          "group": "Будущее время",
          "level": "B2",
          "html": "<p>Действие будет <strong>в процессе</strong> в конкретный момент будущего.</p>\n<pre><code>will be  +  V-ing   →  I will be working</code></pre>\n<ul><li>This time tomorrow I <strong>will be flying</strong> to Paris. <em>(завтра в это время буду в полёте)</em></li><li>Don't call at 8 — I <strong>will be having</strong> dinner.</li></ul>\n<hr>"
        },
        {
          "id": "future-perfect",
          "title": "Future Perfect",
          "group": "Будущее время",
          "level": "B2/C1",
          "html": "<p>Действие <strong>завершится К определённому моменту</strong> в будущем.</p>\n<pre><code>will have  +  V3   →  I will have worked</code></pre>\n<p>Маркер: <strong>by</strong> (к какому-то моменту)</p>\n<ul><li><strong>By</strong> next year, I <strong>will have finished</strong> my studies. <em>(к следующему году — закончу)</em></li><li><strong>By</strong> the time you arrive, we <strong>will have eaten</strong>. <em>(к твоему приходу — уже поедим)</em></li></ul>\n<hr>"
        },
        {
          "id": "future-perfect-continuous",
          "title": "Future Perfect Continuous",
          "group": "Будущее время",
          "level": "C1",
          "html": "<p>Действие будет <strong>длиться какое-то время К моменту</strong> в будущем.</p>\n<pre><code>will have been  +  V-ing   →  I will have been working</code></pre>\n<ul><li><strong>By</strong> December, I <strong>will have been working</strong> here <strong>for</strong> ten years.</li></ul>\n<p><em>(к декабрю — исполнится 10 лет как работаю)</em></p>\n<hr>"
        },
        {
          "id": "все-12-времён-на-одном-глаголе-to-work",
          "title": "Все 12 времён на одном глаголе (to work)",
          "group": "Справочные таблицы",
          "level": null,
          "html": "<table><thead><tr><th>Время</th><th>Утверждение</th><th>Отрицание</th><th>Вопрос</th></tr></thead><tbody><tr><td>Present Simple</td><td>I work</td><td>I don't work</td><td>Do you work?</td></tr><tr><td>Present Continuous</td><td>I am working</td><td>I'm not working</td><td>Are you working?</td></tr><tr><td>Present Perfect</td><td>I have worked</td><td>I haven't worked</td><td>Have you worked?</td></tr><tr><td>Present Perfect Cont.</td><td>I have been working</td><td>I haven't been working</td><td>Have you been working?</td></tr><tr><td>Past Simple</td><td>I worked</td><td>I didn't work</td><td>Did you work?</td></tr><tr><td>Past Continuous</td><td>I was working</td><td>I wasn't working</td><td>Were you working?</td></tr><tr><td>Past Perfect</td><td>I had worked</td><td>I hadn't worked</td><td>Had you worked?</td></tr><tr><td>Past Perfect Cont.</td><td>I had been working</td><td>I hadn't been working</td><td>Had you been working?</td></tr><tr><td>Future Simple</td><td>I will work</td><td>I won't work</td><td>Will you work?</td></tr><tr><td>Future Continuous</td><td>I will be working</td><td>I won't be working</td><td>Will you be working?</td></tr><tr><td>Future Perfect</td><td>I will have worked</td><td>I won't have worked</td><td>Will you have worked?</td></tr><tr><td>Future Perfect Cont.</td><td>I will have been working</td><td>I won't have been working</td><td>Will you have been working?</td></tr></tbody></table>"
        },
        {
          "id": "маркеры-время-быстрая-шпаргалка",
          "title": "Маркеры → время (быстрая шпаргалка)",
          "group": "Справочные таблицы",
          "level": null,
          "html": "<table><thead><tr><th>Увидел маркер</th><th>Скорее всего время</th></tr></thead><tbody><tr><td>always, usually, every day</td><td>Present Simple</td></tr><tr><td>now, at the moment, look!</td><td>Present Continuous</td></tr><tr><td>just, already, yet, ever, never, since, for</td><td>Present Perfect</td></tr><tr><td>yesterday, last week, ago, in 2010</td><td>Past Simple</td></tr><tr><td>while, when (+ длинное действие)</td><td>Past Continuous</td></tr><tr><td>by the time, before, after (в прошлом)</td><td>Past Perfect</td></tr><tr><td>tomorrow, next week, I think</td><td>Future Simple (will)</td></tr><tr><td>plans, intentions, black clouds</td><td>be going to</td></tr><tr><td>by + момент в будущем</td><td>Future Perfect</td></tr></tbody></table>"
        },
        {
          "id": "порядок-изучения-рекомендуемый",
          "title": "Порядок изучения (рекомендуемый)",
          "group": "Справочные таблицы",
          "level": null,
          "html": "<pre><code>A1:  Present Simple → Present Continuous → сравнение этих двух\nA2:  Past Simple → Future Simple (will) → be going to\nB1:  Present Perfect ⭐ → Present Perfect vs Past Simple ⭐⭐ → Past Continuous\nB2:  Past Perfect → Present Perfect Continuous → Future Continuous → Future Perfect\nC1:  Past Perfect Continuous → Future Perfect Continuous</code></pre>\n<p>⭐ = критическая точка, где чаще всего застревают</p>"
        },
        {
          "id": "топ-5-ошибок-русскоговорящих",
          "title": "Топ-5 ошибок русскоговорящих",
          "group": "Справочные таблицы",
          "level": null,
          "html": "<table><thead><tr><th>#</th><th>Ошибка</th><th>Верно</th><th>Причина</th></tr></thead><tbody><tr><td>1</td><td>I have seen him yesterday.</td><td>I <strong>saw</strong> him yesterday.</td><td>есть «вчера» → Past Simple</td></tr><tr><td>2</td><td>He work here.</td><td>He <strong>works</strong> here.</td><td>забыли -s в 3-м лице</td></tr><tr><td>3</td><td>I didn't went.</td><td>I didn't <strong>go</strong>.</td><td>после did — первая форма</td></tr><tr><td>4</td><td>I am knowing it.</td><td>I <strong>know</strong> it.</td><td>know — глагол состояния</td></tr><tr><td>5</td><td>I live here since 2020.</td><td>I <strong>have lived</strong> here since 2020.</td><td>since → Present Perfect</td></tr></tbody></table>"
        }
      ]
    }
  ]
}